data_cleaner/fingerprint_keyer.py
data_cleaner/__init__.py
data_cleaner/georef_api.py
data_cleaner/data_cleaner.py
data_cleaner/capitalizer.py
data_cleaner-0.2.0.dist-info/RECORD
data_cleaner-0.2.0.dist-info/metadata.json
data_cleaner-0.2.0.dist-info/WHEEL
data_cleaner-0.2.0.dist-info/DESCRIPTION.rst
data_cleaner-0.2.0.dist-info/top_level.txt
data_cleaner-0.2.0.dist-info/METADATA
