Metadata-Version: 2.0
Name: data-cleaner
Version: 0.2.0
Summary: Paquete para limpieza de datos, segun estandares del equipo de Datos Argentina
Home-page: https://github.com/datosgobar/data-cleaner
Author: Datos Argentina
Author-email: datos@modernizacion.gob.ar
License: ISCL
Keywords: data-cleaner
Platform: UNKNOWN
Classifier: Development Status :: 2 - Pre-Alpha
Classifier: Intended Audience :: Developers
Classifier: License :: OSI Approved :: ISC License (ISCL)
Classifier: Natural Language :: English
Classifier: Programming Language :: Python :: 3
Classifier: Programming Language :: Python :: 3.7
Requires-Dist: cchardet (==2.1.4)
Requires-Dist: geopandas (==0.5.1)
Requires-Dist: parsley (==1.3)
Requires-Dist: arrow (==0.14.4)
Requires-Dist: Unidecode (==1.1.1)
Requires-Dist: unicodecsv (==0.14.1)
Requires-Dist: xlrd (==1.2.0)
Requires-Dist: PyCRS (==1.0.1)
Requires-Dist: requests (==2.22.0)
